json_storage_manager/__init__.py
json_storage_manager/atomic.py
json_storage_manager/utils.py
json_storage_manager-0.1.8.dist-info/LICENSE
json_storage_manager-0.1.8.dist-info/METADATA
json_storage_manager-0.1.8.dist-info/WHEEL
json_storage_manager-0.1.8.dist-info/top_level.txt
json_storage_manager-0.1.8.dist-info/RECORD
