Metadata-Version: 2.1
Name: json-storage-manager
Version: 0.1.8
Summary: JSON Storage Manager for JSON data stored in text-files
Home-page: https://github.com/hefnawi/json-storage-manager
Author: Ahmed Hefnawi
Author-email: me@ahmedhefnawi.com
License: UNKNOWN
Platform: UNKNOWN
Classifier: Programming Language :: Python :: 3
Classifier: License :: OSI Approved :: MIT License
Classifier: Operating System :: OS Independent
